authenticator/__init__.py
authenticator/cli.py
authenticator/core.py
authenticator/storage.py
authenticator/tui.py
hackauth-0.1.3.dist-info/METADATA
hackauth-0.1.3.dist-info/WHEEL
hackauth-0.1.3.dist-info/entry_points.txt
hackauth-0.1.3.dist-info/licenses/LICENSE
hackauth-0.1.3.dist-info/RECORD
