Metadata-Version: 2.4
Name: hackauth
Version: 0.1.3
Summary: A polished CLI/TUI authenticator and TOTP manager
Project-URL: Homepage, https://github.com/wenfeng110402/Authenticator
Project-URL: Bug Tracker, https://github.com/wenfeng110402/Authenticator/issues
Author-email: Wenfeng Ye <wenfeng110402@icloud.com>
License: GPLv3
License-File: LICENSE
Classifier: Environment :: Console
Classifier: License :: OSI Approved :: GNU General Public License v3 (GPLv3)
Classifier: Operating System :: OS Independent
Classifier: Programming Language :: Python :: 3
Classifier: Topic :: Security
Classifier: Topic :: Utilities
Requires-Python: >=3.9
Requires-Dist: click
Requires-Dist: opencv-python
Requires-Dist: opencv-python-headless; platform_system != 'Windows'
Requires-Dist: pyotp
Requires-Dist: pyperclip
Requires-Dist: qrcode
Requires-Dist: questionary
Requires-Dist: rich
Requires-Dist: textual==7.5.0
